hmbp/__init__.py
hmbp/_version.py
hmbp/fonts.py
hmbp/pgfplots.py
hmbp/plotting.py
hmbp/quick.py
hmbp-0.3.0.dist-info/METADATA
hmbp-0.3.0.dist-info/WHEEL
hmbp-0.3.0.dist-info/top_level.txt
hmbp-0.3.0.dist-info/RECORD
