Metadata-Version: 2.4
Name: hmbp
Version: 0.3.0
Summary: Simple matplotlib and PGFPlots plotting with consistent, publication-ready styling
Author: hmblair
License: MIT
Project-URL: Homepage, https://github.com/hmblair/hmbp
Project-URL: Repository, https://github.com/hmblair/hmbp
Keywords: plotting,matplotlib,pgfplots,latex,visualization,data-science
Classifier: Development Status :: 3 - Alpha
Classifier: Intended Audience :: Science/Research
Classifier: License :: OSI Approved :: MIT License
Classifier: Programming Language :: Python :: 3
Classifier: Programming Language :: Python :: 3.10
Classifier: Programming Language :: Python :: 3.11
Classifier: Programming Language :: Python :: 3.12
Classifier: Topic :: Scientific/Engineering :: Visualization
Requires-Python: >=3.10
Requires-Dist: numpy
Requires-Dist: matplotlib
Provides-Extra: dev
Requires-Dist: pytest; extra == "dev"
